Workbook

Sheet Comparativo_Mercado
A1: Proveedor (archivo) | B1: Marca | C1: Codigo / Modelo | D1: Descripcion | E1: Segmento cliente objetivo | F1: Categoria | G1: Unidad | H1: Costo Neto Unitario (CLP, sin IVA) | I1: Margen objetivo (% sobre venta) | J1: Precio B2B RMG (P B2B, CLP) | K1: Precio Mercado Referencia (CLP) | L1: Vendedor / Fuente de mercado | M1: Brecha vs Mercado (CLP) | N1: Brecha vs Mercado (%) | O1: Observacion
A2: Cristian Hughes | B2: Shell | C2: Helix HX7 10W40 | D2: Aceite Helix HX7 10W40 - mineral/semisintetico, vehiculos livianos | E2: Talleres / Concesionarios | F2: Lubricante | G2: 1 L | H2: 5600 | I2: 0.35 | J2: =H2/(1-I2) -> 8615.3846 | K2: 12990 | L2: Casauto.cl | M2: =K2-J2 -> 4374.6154 | N2: =IFERROR(M2/K2,"N/D") -> 0.33676793 | O2: Match exacto de marca y producto
A3: Cristian Hughes | B3: Shell | C3: Helix Ultra 5W40 | D3: Aceite Helix Ultra 5W40 - 100% sintetico, vehiculos livianos | E3: Talleres / Concesionarios | F3: Lubricante | G3: 4 L | H3: 42990 | I3: 0.35 | J3: =H3/(1-I3) -> 66138.462 | K3: 97520 | L3: Lubricantes en Linea (lista regular $106.000) | M3: =K3-J3 -> 31381.538 | N3: =IFERROR(M3/K3,"N/D") -> 0.32179592 | O3: Match exacto de marca y producto
A4: Cristian Hughes | B4: Shell | C4: Rimula R4 L 15W40 CK-4 | D4: Aceite Rimula R4L 15W40 CK-4 - camiones/flotas diesel | E4: Flotas / Construccion | F4: Lubricante | G4: 4 L | H4: 18990 | I4: 0.35 | J4: =H4/(1-I4) -> 29215.385 | K4: 28490 | L4: Promedio GM Comercializadora / MercadoLibre ($26.990-$29.990) | M4: =K4-J4 -> -725.38462 | N4: =IFERROR(M4/K4,"N/D") -> -0.025461025 | O4: Match exacto de marca y producto
A5: Cristian Hughes | B5: Shell | C5: Rimula R4X 15W40 CI-4 | D5: Aceite Rimula R4X 15W40 CI-4 - camiones/flotas diesel | E5: Flotas / Construccion | F5: Lubricante | G5: 4 L | H5: 17500 | I5: 0.35 | J5: =H5/(1-I5) -> 26923.077 | K5: 24990 | L5: Chile Baterias | M5: =K5-J5 -> -1933.0769 | N5: =IFERROR(M5/K5,"N/D") -> -0.077354019 | O5: Match exacto de marca y producto
A6: Cristian Hughes | B6: Platin | C6: 55D23R / 60Ah | D6: Bateria Platin 60Ah 500CCA - automoviles/camionetas | E6: Talleres / Concesionarios | F6: Bateria | G6: Unidad | H6: 40500 | I6: 0.35 | J6: =H6/(1-I6) -> 62307.692 | K6: 82400 | L6: Ventas El Garage (rango $74.900-$89.900) | M6: =K6-J6 -> 20092.308 | N6: =IFERROR(M6/K6,"N/D") -> 0.24383869 | O6: Match exacto de marca; CCA similar
A7: Cristian Hughes | B7: Platin | C7: Q85 EFB / 65Ah | D7: Bateria Platin Q85 EFB Start-Stop 65Ah - vehiculos modernos | E7: Concesionarios | F7: Bateria | G7: Unidad | H7: 68500 | I7: 0.35 | J7: =H7/(1-I7) -> 105384.62 | K7: 160000 | L7: Referencia interna del proveedor (competencia $120.000-$200.000) | M7: =K7-J7 -> 54615.385 | N7: =IFERROR(M7/K7,"N/D") -> 0.34134615 | O7: Dato de competencia ya incluido en cotizacion CH
A8: Vistony | B8: Vistony Attom | C8: S320 5W30 ACEA C3/API SN | D8: Aceite Attom S320 5W30 - sintetico premium, vehiculos livianos | E8: Talleres / Concesionarios | F8: Lubricante | G8: 1 L | H8: 4478 | I8: 0.35 | J8: =H8/(1-I8) -> 6889.2308 | K8: 19990 | L8: Casauto.cl | M8: =K8-J8 -> 13100.769 | N8: =IFERROR(M8/K8,"N/D") -> 0.65536614 | O8: Match exacto de marca y producto
A9: Vistony | B9: Vistony Sintek Oil | C9: S210 10W40 ACEA A3/B4 | D9: Aceite Sintek Oil S210 10W40 - semisintetico, vehiculos livianos | E9: Talleres / Concesionarios | F9: Lubricante | G9: 1 L | H9: 4809 | I9: 0.35 | J9: =H9/(1-I9) -> 7398.4615 | K9: 21990 | L9: Casauto.cl | M9: =K9-J9 -> 14591.538 | N9: =IFERROR(M9/K9,"N/D") -> 0.66355336 | O9: Match exacto de marca y producto
A10: SalfaSur | B10: Auster | C10: MAXFORCE 15W40 CK-4 | D10: Aceite Auster Maxforce 15W40 CK-4 - flotas/camiones diesel | E10: Flotas / Construccion | F10: Lubricante | G10: 1 L | H10: 3385 | I10: 0.35 | J10: =H10/(1-I10) -> 5207.6923 | K10: N/D | L10: Marca propia red SSUR - sin venta minorista independiente | M10: N/D | N10: N/D | O10: Sin comparable directo de mercado abierto; referencia categoria Shell Rimula CK-4
A11: SalfaSur | B11: Auster | C11: MAXTECH PRO RX 5W30 | D11: Aceite Auster Maxtech Pro RX 5W30 - vehiculos livianos | E11: Talleres / Concesionarios | F11: Lubricante | G11: 1 L | H11: 3116 | I11: 0.35 | J11: =H11/(1-I11) -> 4793.8462 | K11: N/D | L11: Marca propia red SSUR - sin venta minorista independiente | M11: N/D | N11: N/D | O11: Sin comparable directo de mercado abierto; referencia categoria Attom S320
A12: SalfaSur | B12: YOKO G&B | C12: N40L / 40Ah | D12: Bateria Yoko 40Ah - automoviles chicos | E12: Talleres / Concesionarios | F12: Bateria | G12: Unidad | H12: 35579 | I12: 0.35 | J12: =H12/(1-I12) -> 54736.923 | K12: 56260 | L12: Tienda Salfa (rango inferior de catalogo Yoko) | M12: =K12-J12 -> 1523.0769 | N12: =IFERROR(M12/K12,"N/D") -> 0.02707211 | O12: Match exacto de marca; mapeo de Ah aproximado
A13: SalfaSur | B13: YOKO G&B | C13: 55D23L / 60Ah | D13: Bateria Yoko 60Ah 500CCA - automoviles/camionetas | E13: Talleres / Concesionarios | F13: Bateria | G13: Unidad | H13: 53440 | I13: 0.35 | J13: =H13/(1-I13) -> 82215.385 | K13: 107000 | L13: Neumarex Temuco (rango $95.000-$119.000) | M13: =K13-J13 -> 24784.615 | N13: =IFERROR(M13/K13,"N/D") -> 0.23163192 | O13: Match exacto de marca y medida
A14: SalfaSur | B14: YOKO G&B | C14: NX120-7L / 90Ah | D14: Bateria Yoko 90Ah - camionetas/SUV | E14: Talleres / Flotas | F14: Bateria | G14: Unidad | H14: 70842 | I14: 0.35 | J14: =H14/(1-I14) -> 108987.69 | K14: 140190 | L14: Covepa | M14: =K14-J14 -> 31202.308 | N14: =IFERROR(M14/K14,"N/D") -> 0.22257156 | O14: Match exacto de marca y medida
A15: SalfaSur | B15: YOKO G&B | C15: N150 / 150Ah | D15: Bateria Yoko 150Ah - camiones/buses | E15: Flotas / Construccion | F15: Bateria | G15: Unidad | H15: 129164 | I15: 0.35 | J15: =H15/(1-I15) -> 198713.85 | K15: 150000 | L15: Promedio categoria 150Ah (Implementos, TTP, Raco) - marcas equivalentes | M15: =K15-J15 -> -48713.846 | N15: =IFERROR(M15/K15,"N/D") -> -0.32475897 | O15: Sin listado YOKO especifico; referencia de categoria 150Ah
A16: SalfaSur | B16: Kumho | C16: 225/60R16 KR26 98H | D16: Neumatico Kumho 225/60R16 - automoviles/SUV | E16: Concesionarios / Talleres | F16: Neumatico | G16: Unidad | H16: 59516 | I16: 0.35 | J16: =H16/(1-I16) -> 91563.077 | K16: 80000 | L16: Neumax.cl (modelo equivalente Kumho Power Max, mismo aro/medida) | M16: =K16-J16 -> -11563.077 | N16: =IFERROR(M16/K16,"N/D") -> -0.14453846 | O16: Match de marca; modelo comparable de catalogo similar
D18: PROMEDIOS (solo items con dato de mercado) | H18: =AVERAGE(H2:H16) -> 37227.267 | J18: =AVERAGE(J2:J16) -> 57272.718 | K18: =AVERAGEIF(K2:K16,">0") -> 75524.615 | N18: =AVERAGEIF(N2:N16,"<>N/D") -> 0.19014087

Sheet Resumen_KPI
A1: RESUMEN EJECUTIVO - RMG AUTO PARTS / Modelo de negocio Talleres-Flotas-Concesionarios-Construccion
A3: Metodologia de precio
A4: Precio B2B RMG = Costo Neto Proveedor / (1 - Margen objetivo)
A5: Margen objetivo aplicado = 35% sobre el precio final de venta (no sobre el costo)
A6: Ejemplo: Costo $10.000 -> P B2B = 10.000 / 0.65 = $15.385 (margen $5.385 = 35% de $15.385)
A8: Categoria | B8: N° SKU analizados | C8: Costo Neto Prom. | D8: P B2B Promedio | E8: Mercado Promedio | F8: Brecha Promedio %
A9: Lubricante | B9: =COUNTIF(Comparativo_Mercado!F2:F16,A9) -> 8 | C9: =AVERAGEIF(Comparativo_Mercado!F2:F16,A9,Comparativo_Mercado!H2:H16) -> 12608.5 | D9: =AVERAGEIF(Comparativo_Mercado!F2:F16,A9,Comparativo_Mercado!J2:J16) -> 19397.692 | E9: =IFERROR(AVERAGEIFS(Comparativo_Mercado!K2:K16,Comparativo_Mercado!F2:F16,A9,Comparativo_Mercado!K2:K16,">0"),"N/D") -> 34328.333 | F9: =IFERROR(AVERAGEIFS(Comparativo_Mercado!N2:N16,Comparativo_Mercado!F2:F16,A9,Comparativo_Mercado!K2:K16,">0"),"N/D") -> 0.31244472
A10: Bateria | B10: =COUNTIF(Comparativo_Mercado!F2:F16,A10) -> 6 | C10: =AVERAGEIF(Comparativo_Mercado!F2:F16,A10,Comparativo_Mercado!H2:H16) -> 66337.5 | D10: =AVERAGEIF(Comparativo_Mercado!F2:F16,A10,Comparativo_Mercado!J2:J16) -> 102057.69 | E10: =IFERROR(AVERAGEIFS(Comparativo_Mercado!K2:K16,Comparativo_Mercado!F2:F16,A10,Comparativo_Mercado!K2:K16,">0"),"N/D") -> 115975 | F10: =IFERROR(AVERAGEIFS(Comparativo_Mercado!N2:N16,Comparativo_Mercado!F2:F16,A10,Comparativo_Mercado!K2:K16,">0"),"N/D") -> 0.12361691
A11: Neumatico | B11: =COUNTIF(Comparativo_Mercado!F2:F16,A11) -> 1 | C11: =AVERAGEIF(Comparativo_Mercado!F2:F16,A11,Comparativo_Mercado!H2:H16) -> 59516 | D11: =AVERAGEIF(Comparativo_Mercado!F2:F16,A11,Comparativo_Mercado!J2:J16) -> 91563.077 | E11: =IFERROR(AVERAGEIFS(Comparativo_Mercado!K2:K16,Comparativo_Mercado!F2:F16,A11,Comparativo_Mercado!K2:K16,">0"),"N/D") -> 80000 | F11: =IFERROR(AVERAGEIFS(Comparativo_Mercado!N2:N16,Comparativo_Mercado!F2:F16,A11,Comparativo_Mercado!K2:K16,">0"),"N/D") -> -0.14453846
A14: Lectura del analisis
A15: 1) En lubricantes y baterias de marca propia/exclusiva (Auster - SalfaSur), no existe venta minorista independiente verificable: son marcas cerradas a la red del distribuidor, lo que es una barrera y a la vez una oportunidad si RMG negocia exclusividad territorial.
A16: 2) En marcas con venta retail abierta (Shell, Platin, Vistony/Attom, Yoko, Kumho) el precio B2B calculado con margen 35% queda sistematicamente por debajo del precio de mercado minorista, validando espacio para vender B2B a talleres/flotas y que estos mantengan su propio margen de reventa.
A17: 3) La brecha es mayor en lubricantes de marca premium (Shell Helix Ultra, Attom) que en baterias, donde el costo de logistica/peso reduce el margen relativo del canal minorista.
A18: 4) Para Auster y otras lineas propias, se recomienda fijar P B2B con el mismo criterio (35%) y validar contra cotizaciones directas a talleres, dado que no hay precio de mercado publico de referencia.
