Workbook

Sheet Portada
B2: RMG AUTO PARTS — Modelo de Negocio por Segmento
B3: Integracion de Matriz Maestra (653 SKU) + Productos por Nicho + Benchmark de Mercado
B4: Santiago, Region Metropolitana - Chile - 2026
B6: Que responde este archivo
B7: Para cada producto priorizado por segmento (52 combinaciones definidas en la hoja Productos_por_Nicho original del usuario), este modelo responde 3 preguntas: que vender, en que presentacion, y que proveedor conviene usar hoy (Cristian Hughes, Vistony o SalfaSur) segun el costo real por unidad normalizada, cruzado contra el precio de mercado de referencia.
B9: Parametros
B10: Margen objetivo B2B RMG (sobre precio de venta) | D10: 0.35
B12: Contenido del libro
B13: - Matriz_Maestra — las 653 SKU de Cristian Hughes, Vistony y SalfaSur con Tipo, Presentacion, Envase y Precio Unitario calculados
B14: - Comparativo_Proveedor — para cada producto priorizado, todas las opciones de proveedor disponibles lado a lado
B15: - Recomendacion_por_Segmento — el resultado final: que vender, en que presentacion, con que proveedor, a que precio, y como queda vs el mercado
B16: - Resumen_Segmento — vista agregada por segmento (cuantos productos, brecha promedio vs mercado)
B17: - Notas — criterios de match usados y productos sin equivalente en el catalogo actual

Sheet Matriz_Maestra
A1: Proveedor | B1: Marca | C1: Categoria | D1: Codigo | E1: Descripcion Original | F1: Precio Original Contado (CLP) | G1: Precio Original Credito (CLP) | H1: Tipo | I1: Presentacion (volumen) | J1: Envase | K1: Contenido Normalizado | L1: Unidad | M1: Cantidad x Caja (Q) | N1: Precio Unitario (CLP) | O1: Precio Unitario Normalizado (CLP/L, CLP/Kg o CLP/Un) | P1: Stock (si aplica) | Q1: Nota
A2: Vistony | B2: Vistony | C2: Lubricante | D2: 1000544 | E2: CAJ04 ATTOM S320 SAE 5W-30 ACEA C3/API SN DE 5 L | F2: 87780 | G2: 93046 | H2: ATTOM S320 SAE 5W-30 | I2: 5 L | J2: Bidon | K2: 5 | L2: L | M2: 4 | N2: =F2/M2 -> 21945 | O2: =N2/K2 -> 4389
A3: Vistony | B3: Vistony | C3: Refrigerante/Aditivo Diesel | D3: 1200009 | E3: CAJ06 LIQUIDO PARA RADIADOR VERDE DE 1 GAL | F3: 15254 | G3: 16169 | H3: LIQUIDO PARA RADIADOR VERDE | I3: 1 GAL | J3: Galon | K3: 3.785 | L3: L | M3: 6 | N3: =F3/M3 -> 2542.3333 | O3: =N3/K3 -> 671.68648
A4: Vistony | B4: Vistony | C4: Lubricante | D4: 1000560 | E4: CAJ04 SINTEK OIL S 210 SAE 10W40 ACEA A3/B4 - API SN DE 4L | F4: 67674 | G4: 71735 | H4: SINTEK OIL S 210 SAE 10W40 | I4: 4 L | J4: Galon | K4: 4 | L4: L | M4: 4 | N4: =F4/M4 -> 16918.5 | O4: =N4/K4 -> 4229.625
A5: Vistony | B5: Vistony | C5: Refrigerante/Aditivo Diesel | D5: 1200105 | E5: CAJ06 COOLANT ICE FREEZE ORGANIC (OAT) 50/50 GREEN - 5 IDIOMAS DE 4L | F5: 54652 | G5: 57931 | H5: COOLANT ICE FREEZE ORGANIC (OAT) 50/50 GREEN - 5 IDIOMAS | I5: 4 L | J5: Galon | K5: 4 | L5: L | M5: 6 | N5: =F5/M5 -> 9108.6667 | O5: =N5/K5 -> 2277.1667
A6: Vistony | B6: Vistony | C6: Lubricante | D6: 1000618 | E6: CAJ12 TRANSMEC SYNTHETIC API GL-4 SAE 75W90 DE 1L | F6: 69392 | G6: 73555 | H6: TRANSMEC SYNTHETIC SAE 75W90 | I6: 1 L | J6: Frasco/Botella | K6: 1 | L6: L | M6: 12 | N6: =F6/M6 -> 5782.6667 | O6: =N6/K6 -> 5782.6667
A7: Vistony | B7: Vistony | C7: Refrigerante/Aditivo Diesel | D7: 1200083 | E7: CAJ06 COOLANT ICE FREEZE ORGANICO (OAT) 50/50 LONG LIFE FUCHSIA DE 4L | F7: 54201 | G7: 57453 | H7: COOLANT ICE FREEZE ORGANICO (OAT) 50/50 LONG LIFE FUCHSIA | I7: 4 L | J7: Galon | K7: 4 | L7: L | M7: 6 | N7: =F7/M7 -> 9033.5 | O7: =N7/K7 -> 2258.375
A8: Vistony | B8: Vistony | C8: Lubricante | D8: 1000738 | E8: BAL DRAULA H 68 DE 5 GL | F8: 47502 | G8: 50353 | H8: DRAULA H 68 | I8: 5 GL | J8: Balde | K8: 18.925 | L8: L | M8: 1 | N8: =F8/M8 -> 47502 | O8: =N8/K8 -> 2510.0132
A9: Vistony | B9: Vistony | C9: Lubricante | D9: 1000045 | E9: CAJ12 TRANSMISION AUTOMATICA - ATF DE 1/4 GL | F9: 55593 | G9: 58928 | H9: TRANSMISION AUTOMATICA - ATF | I9: 1/4 GL | J9: Frasco/Botella | K9: 0.9463 | L9: L | M9: 12 | N9: =F9/M9 -> 4632.75 | O9: =N9/K9 -> 4895.6462
A10: Vistony | B10: Vistony | C10: Lubricante | D10: 1000545 | E10: CIL ATTOM S320 SAE 5W-30 ACEA C3/API SN DE 55 GL | F10: 810806 | G10: 859454 | H10: ATTOM S320 SAE 5W-30 | I10: 55 GL | J10: Tambor/Cilindro | K10: 208.175 | L10: L | M10: 1 | N10: =F10/M10 -> 810806 | O10: =N10/K10 -> 3894.8289
A11: Vistony | B11: Vistony | C11: Lubricante | D11: 1000130 | E11: CAJ12 GEAR OIL GL-5 SAE 80W90 DE 0.946 LT | F11: 53635 | G11: 56853 | H11: GEAR OIL GL-5 SAE 80W90 | I11: 0.946 LT | J11: Frasco/Botella | K11: 0.946 | L11: L | M11: 12 | N11: =F11/M11 -> 4469.5833 | O11: =N11/K11 -> 4724.7181
A12: Vistony | B12: Vistony | C12: Lubricante | D12: 1000806 | E12: CAJ06 BLINDAX DUO SAE 10W40 DE 4 LT | F12: 72793 | G12: 77160 | H12: BLINDAX DUO SAE 10W40 | I12: 4 LT | J12: Galon | K12: 4 | L12: L | M12: 6 | N12: =F12/M12 -> 12132.167 | O12: =N12/K12 -> 3033.0417
A13: Vistony | B13: Vistony | C13: Refrigerante/Aditivo Diesel | D13: 1200079 | E13: CAJ06 COOLANT ICE FREEZE ORGANICO (OAT) 33% GREEN DE 1 GL | F13: 43747 | G13: 46371 | H13: COOLANT ICE FREEZE ORGANICO (OAT) 33% GREEN | I13: 1 GL | J13: Galon | K13: 3.785 | L13: L | M13: 6 | N13: =F13/M13 -> 7291.1667 | O13: =N13/K13 -> 1926.332
... A65: Vistony | B65: Vistony | C65: Grasa | D65: 1100290 | E65: CAJ12 GRAFITADA PARA PALIERES DE 210 GRS | F65: 15682 | G65: 16623 | H65: GRAFITADA PARA PALIERES | I65: 210 GRS | J65: Tarro | K65: 0.21 | L65: KG | M65: 12 | N65: =F65/M65 -> 1306.8333 | O65: =N65/K65 -> 6223.0159
A66: Vistony | B66: Vistony | C66: Lubricante | D66: 1000786 | E66: LIT DRAULA H 68 | F66: 1981 | G66: 2100 | H66: DRAULA H 68 | I66: 1 L | J66: Frasco/Botella | K66: 1 | L66: L | M66: 1 | N66: =F66/M66 -> 1981 | O66: =N66/K66 -> 1981 | Q66: LIT = suelto, asumido 1L
A67: Vistony | B67: Vistony | C67: Lubricante | D67: 1000779 | E67: CAJ12 RAYVON FORK OIL 10W DE 1 L | F67: 57964 | G67: 61442 | H67: RAYVON FORK OIL 10W | I67: 1 L | J67: Frasco/Botella | K67: 1 | L67: L | M67: 12 | N67: =F67/M67 -> 4830.3333 | O67: =N67/K67 -> 4830.3333
A68: Vistony | B68: Vistony | C68: Lubricante | D68: 1000839 | E68: CIL FORZA TRUCK SAE 20W-50 DE 55 GAL | F68: 537969 | G68: 570247 | H68: FORZA TRUCK SAE 20W-50 | I68: 55 GAL | J68: Tambor/Cilindro | K68: 208.175 | L68: L | M68: 1 | N68: =F68/M68 -> 537969 | O68: =N68/K68 -> 2584.2152
A69: Vistony | B69: Vistony | C69: Lubricante | D69: 1000708 | E69: BAL VELTRON ISO VG 680 DE 5 GAL | F69: 65799 | G69: 69747 | H69: VELTRON ISO VG 680 | I69: 5 GAL | J69: Balde | K69: 18.925 | L69: L | M69: 1 | N69: =F69/M69 -> 65799 | O69: =N69/K69 -> 3476.8296
A70: Vistony | B70: Vistony | C70: Grasa | D70: 1100276 | E70: CAJ24 EP-2 LITHIUM MULTIPROPOSITO ROJO DE 210 GRS | F70: 30055 | G70: 31858 | H70: EP-2 LITHIUM MULTIPROPOSITO ROJO | I70: 210 GRS | J70: Tarro | K70: 0.21 | L70: KG | M70: 24 | N70: =F70/M70 -> 1252.2917 | O70: =N70/K70 -> 5963.2937
A71: Vistony | B71: Vistony | C71: Lubricante | D71: 1000127 | E71: CAJ12 GEAR OIL GL-5 SAE 85W140 DE 0.946 LT | F71: 50468 | G71: 53496 | H71: GEAR OIL GL-5 SAE 85W140 | I71: 0.946 LT | J71: Frasco/Botella | K71: 0.946 | L71: L | M71: 12 | N71: =F71/M71 -> 4205.6667 | O71: =N71/K71 -> 4445.7364
A72: Vistony | B72: Vistony | C72: Lubricante | D72: 1000083 | E72: BAL DRAULA H 46 DE 5 GAL | F72: 45086 | G72: 47791 | H72: DRAULA H 46 | I72: 5 GAL | J72: Balde | K72: 18.925 | L72: L | M72: 1 | N72: =F72/M72 -> 45086 | O72: =N72/K72 -> 2382.3514
A73: Vistony | B73: Vistony | C73: Quimico/Cuidado vehicular | D73: 1400079 | E73: CAJ12 LIMPIA RADIADOR DE LATA DE 300 ML | F73: 34467 | G73: 36535 | H73: LIMPIA RADIADOR DE LATA | I73: 300 ML | J73: Sachet/Spray | K73: 0.3 | L73: L | M73: 12 | N73: =F73/M73 -> 2872.25 | O73: =N73/K73 -> 9574.1667
A74: Vistony | B74: Vistony | C74: Lubricante | D74: 1000440 | E74: BAL FORZA VIS SAE 25W60 API CF-4 DE 5 GAL | F74: 59317 | G74: 62876 | H74: FORZA VIS SAE 25W60 | I74: 5 GAL | J74: Balde | K74: 18.925 | L74: L | M74: 1 | N74: =F74/M74 -> 59317 | O74: =N74/K74 -> 3134.3197
A75: Vistony | B75: Vistony | C75: Lubricante | D75: 1000143 | E75: CIL GEAR OIL GL-5 SAE 80W90 DE 55 GL | F75: 696805 | G75: 738613 | H75: GEAR OIL GL-5 SAE 80W90 | I75: 55 GL | J75: Tambor/Cilindro | K75: 208.175 | L75: L | M75: 1 | N75: =F75/M75 -> 696805 | O75: =N75/K75 -> 3347.2079
A76: Vistony | B76: Vistony | C76: Grasa | D76: 1100284 | E76: BAL COMPLEJO DE LITIO NLGI 2 DE 35 LIBRAS | F76: 74907 | G76: 79401 | H76: COMPLEJO DE LITIO NLGI 2 | I76: 35 LIBRAS | J76: Balde | K76: 15.8757 | L76: KG | M76: 1 | N76: =F76/M76 -> 74907 | O76: =N76/K76 -> 4718.3431
A77: Vistony | B77: Vistony | C77: Aditivo | D77: 1600002 | E77: CAJ12 ADITIVO ESPECIAL PARA DIESEL DE 443 ML | F77: 35078 | G77: 37183 | H77: ADITIVO ESPECIAL PARA DIESEL | I77: 443 ML | J77: Frasco/Botella | K77: 0.443 | L77: L | M77: 12 | N77: =F77/M77 -> 2923.1667 | O77: =N77/K77 -> 6598.5704
A78: Vistony | B78: Vistony | C78: Lubricante | D78: 1200141 | E78: CAJ06 AGUA P/ BATERIA DE 1 GAL | F78: 12550 | G78: 13303 | H78: AGUA P/ BATERIA | I78: 1 GAL | J78: Galon | K78: 3.785 | L78: L | M78: 6 | N78: =F78/M78 -> 2091.6667 | O78: =N78/K78 -> 552.61999
... A279: Vistony | B279: Vistony | C279: Grasa | D279: 1100045 | E279: CAJ12 EP-2 LITHIUM MULTIPROPOSITO ROJO DE 453 GRS | F279: 28897 | G279: 30631 | H279: EP-2 LITHIUM MULTIPROPOSITO ROJO | I279: 453 GRS | J279: Tarro | K279: 0.453 | L279: KG | M279: 12 | N279: =F279/M279 -> 2408.0833 | O279: =N279/K279 -> 5315.8572
A280: Vistony | B280: Vistony | C280: Grasa | D280: 1100130 | E280: CIL COMPLEJO DE LITIO NLGI 2 CILINDRO | F280: 1268883 | G280: 1345016 | H280: COMPLEJO DE LITIO NLGI 2 CILINDRO | I280: Cilindro/Tambor | J280: Tambor/Cilindro | M280: 1 | N280: =F280/M280 -> 1268883 | Q280: Sin dato de volumen - revisar manualmente
A281: Vistony | B281: Vistony | C281: Grasa | D281: 1100138 | E281: CAJ12 EP-2 LITHIUM MULTIPROPOSITO AMARILLO DE 210 GRS | F281: 13677 | G281: 14497 | H281: EP-2 LITHIUM MULTIPROPOSITO AMARILLO | I281: 210 GRS | J281: Tarro | K281: 0.21 | L281: KG | M281: 12 | N281: =F281/M281 -> 1139.75 | O281: =N281/K281 -> 5427.381
A282: Vistony | B282: Vistony | C282: Grasa | D282: 1100141 | E282: CAJ12 GRAFITADA PARA PALIERES DE 210 GRS | F282: 14292 | G282: 15149 | H282: GRAFITADA PARA PALIERES | I282: 210 GRS | J282: Tarro | K282: 0.21 | L282: KG | M282: 12 | N282: =F282/M282 -> 1191 | O282: =N282/K282 -> 5671.4286
A283: Vistony | B283: Vistony | C283: Grasa | D283: 1100142 | E283: CAJ24 GRAFITADA PARA PALIERES DE 210 GRS | F283: 28584 | G283: 30299 | H283: GRAFITADA PARA PALIERES | I283: 210 GRS | J283: Tarro | K283: 0.21 | L283: KG | M283: 24 | N283: =F283/M283 -> 1191 | O283: =N283/K283 -> 5671.4286
A284: Vistony | B284: Vistony | C284: Grasa | D284: 1100144 | E284: CAJ12 EP-2 LITHIUM MULTIPROPOSITO ROJO DE 210 GRS | F284: 13677 | G284: 14497 | H284: EP-2 LITHIUM MULTIPROPOSITO ROJO | I284: 210 GRS | J284: Tarro | K284: 0.21 | L284: KG | M284: 12 | N284: =F284/M284 -> 1139.75 | O284: =N284/K284 -> 5427.381
A285: Vistony | B285: Vistony | C285: Grasa | D285: 1100145 | E285: CAJ24 EP-2 LITHIUM MULTIPROPOSITO ROJO DE 210 GRS | F285: 25250 | G285: 26765 | H285: EP-2 LITHIUM MULTIPROPOSITO ROJO | I285: 210 GRS | J285: Tarro | K285: 0.21 | L285: KG | M285: 24 | N285: =F285/M285 -> 1052.0833 | O285: =N285/K285 -> 5009.9206
A286: Vistony | B286: Vistony | C286: Grasa | D286: 1100153 | E286: CAJ12 H-3 PARA RODAMIENTOS ROJO DE 210 GRS | F286: 12698 | G286: 13460 | H286: H-3 PARA RODAMIENTOS ROJO | I286: 210 GRS | J286: Tarro | K286: 0.21 | L286: KG | M286: 12 | N286: =F286/M286 -> 1058.1667 | O286: =N286/K286 -> 5038.8889
A287: Vistony | B287: Vistony | C287: Grasa | D287: 1100198 | E287: CIL COMPLEX MOLY NLGI 2 DE 400 LB | F287: 1335552 | G287: 1415685 | H287: COMPLEX MOLY NLGI 2 | I287: 400 LB | J287: Tambor/Cilindro | K287: 181.4368 | L287: KG | M287: 1 | N287: =F287/M287 -> 1335552 | O287: =N287/K287 -> 7360.9764
A288: Vistony | B288: Vistony | C288: Grasa | D288: 1100263 | E288: CAJ24 EP-2 LITHIUM MULTIPROPOSITO AMARILLO DE 210 GRS | F288: 22156 | G288: 23486 | H288: EP-2 LITHIUM MULTIPROPOSITO AMARILLO | I288: 210 GRS | J288: Tarro | K288: 0.21 | L288: KG | M288: 24 | N288: =F288/M288 -> 923.16667 | O288: =N288/K288 -> 4396.0317
A289: Vistony | B289: Vistony | C289: Refrigerante/Aditivo Diesel | D289: 1200010 | E289: GL LIQUIDO PARA RADIADOR VERDE DE 1 GAL | F289: 2370 | G289: 2512 | H289: LIQUIDO PARA RADIADOR VERDE | I289: 1 GAL | J289: Galon | K289: 3.785 | L289: L | M289: 1 | N289: =F289/M289 -> 2370 | O289: =N289/K289 -> 626.15588
A290: Vistony | B290: Vistony | C290: Refrigerante/Aditivo Diesel | D290: 1200024 | E290: FRA LIQUIDO PARA RADIADOR DE 1/4 GL | F290: 715 | G290: 758 | H290: LIQUIDO PARA RADIADOR | I290: 1/4 GL | J290: Frasco/Botella | K290: 0.9463 | L290: L | M290: 1 | N290: =F290/M290 -> 715 | O290: =N290/K290 -> 755.57434
A291: Vistony | B291: Vistony | C291: Grasa | D291: 1100271 | E291: CIL COMPLEX MOLY NLGI 2 DE 400 LB | F291: 1335552 | G291: 1415685 | H291: COMPLEX MOLY NLGI 2 | I291: 400 LB | J291: Tambor/Cilindro | K291: 181.4368 | L291: KG | M291: 1 | N291: =F291/M291 -> 1335552 | O291: =N291/K291 -> 7360.9764
A292: Vistony | B292: Vistony | C292: Refrigerante/Aditivo Diesel | D292: 1200036 | E292: GL LIQUIDO PARA RADIADOR ROJO - 1 GAL | F292: 2143 | G292: 2271 | H292: LIQUIDO PARA RADIADOR ROJO - 1 GAL | I292: 1 GAL | J292: Galon | K292: 3.785 | L292: L | M292: 1 | N292: =F292/M292 -> 2143 | O292: =N292/K292 -> 566.1823
... A321: Vistony | B321: Vistony | C321: Lubricante | D321: 1400003 | E321: FRA MOTOR FLUSH DE 443 ML | F321: 2535 | G321: 2687 | H321: MOTOR FLUSH | I321: 443 ML | J321: Frasco/Botella | K321: 0.443 | L321: L | M321: 1 | N321: =F321/M321 -> 2535 | O321: =N321/K321 -> 5722.3476
A322: Vistony | B322: Vistony | C322: Quimico/Cuidado vehicular | D322: 1400013 | E322: GL BRILLANTA - PROTEGE Y BRILLA | F322: 9350 | G322: 9911 | H322: BRILLANTA - PROTEGE Y BRILLA | I322: 1 GAL | J322: Galon | K322: 3.785 | L322: L | M322: 1 | N322: =F322/M322 -> 9350 | O322: =N322/K322 -> 2470.2774 | Q322: Sin volumen explicito, formato GL asumido 1 galon (3.785L)
A323: Vistony | B323: Vistony | C323: Quimico/Cuidado vehicular | D323: 1400016 | E323: FRA SILICONA WHITE CON AROMA FRESA DE 300 ML | F323: 1507 | G323: 1598 | H323: SILICONA WHITE CON AROMA FRESA | I323: 300 ML | J323: Frasco/Botella | K323: 0.3 | L323: L | M323: 1 | N323: =F323/M323 -> 1507 | O323: =N323/K323 -> 5023.3333
A324: Vistony | B324: Vistony | C324: Quimico/Cuidado vehicular | D324: 1400012 | E324: CAJ06 BRILLANTA - PROTEGE Y BRILLA | F324: 57291 | G324: 60729 | H324: BRILLANTA - PROTEGE Y BRILLA | I324: 1 GAL | J324: Galon | K324: 3.785 | L324: L | M324: 6 | N324: =F324/M324 -> 9548.5 | O324: =N324/K324 -> 2522.7213 | Q324: Sin volumen explicito en caja, asumido 1 galon (3.785L) por unidad
A325: Vistony | B325: Vistony | C325: Quimico/Cuidado vehicular | D325: 1400019 | E325: FRA LIMPIA PARABRISAS DE 1 LT | F325: 1331 | G325: 1411 | H325: LIMPIA PARABRISAS | I325: 1 LT | J325: Frasco/Botella | K325: 1 | L325: L | M325: 1 | N325: =F325/M325 -> 1331 | O325: =N325/K325 -> 1331
A326: Vistony | B326: Vistony | C326: Quimico/Cuidado vehicular | D326: 1400014 | E326: CAJ12 SILICONA WHITE CON AROMA FRESA DE 300 ML | F326: 18472 | G326: 19581 | H326: SILICONA WHITE CON AROMA FRESA | I326: 300 ML | J326: Sachet/Spray | K326: 0.3 | L326: L | M326: 12 | N326: =F326/M326 -> 1539.3333 | O326: =N326/K326 -> 5131.1111
A327: Vistony | B327: Vistony | C327: Quimico/Cuidado vehicular | D327: 1400025 | E327: GL SILICONA WHITE CON AROMA FRESA DE 1GL | F327: 10710 | G327: 11352 | H327: SILICONA WHITE CON AROMA FRESA | I327: 1 GL | J327: Galon | K327: 3.785 | L327: L | M327: 1 | N327: =F327/M327 -> 10710 | O327: =N327/K327 -> 2829.5905
A328: Vistony | B328: Vistony | C328: Quimico/Cuidado vehicular | D328: 1400015 | E328: CAJ24 SILICONA WHITE CON AROMA FRESA DE 300 ML | F328: 36944 | G328: 39161 | H328: SILICONA WHITE CON AROMA FRESA | I328: 300 ML | J328: Sachet/Spray | K328: 0.3 | L328: L | M328: 24 | N328: =F328/M328 -> 1539.3333 | O328: =N328/K328 -> 5131.1111
A329: Vistony | B329: Vistony | C329: Quimico/Cuidado vehicular | D329: 1400028 | E329: FRA BRILLANTA - PROTEGE Y BRILLA DE 300 ML | F329: 1595 | G329: 1690 | H329: BRILLANTA - PROTEGE Y BRILLA | I329: 300 ML | J329: Frasco/Botella | K329: 0.3 | L329: L | M329: 1 | N329: =F329/M329 -> 1595 | O329: =N329/K329 -> 5316.6667
A330: Vistony | B330: Vistony | C330: Quimico/Cuidado vehicular | D330: 1400017 | E330: CAJ12 LIMPIA PARABRISAS DE 1 LT | F330: 16317 | G330: 17296 | H330: LIMPIA PARABRISAS | I330: 1 LT | J330: Frasco/Botella | K330: 1 | L330: L | M330: 12 | N330: =F330/M330 -> 1359.75 | O330: =N330/K330 -> 1359.75
A331: Vistony | B331: Vistony | C331: Quimico/Cuidado vehicular | D331: 1400036 | E331: GL SHAMPOO SUPER CONCENTRADO DE GAL | F331: 7308 | G331: 7746 | H331: SHAMPOO SUPER CONCENTRADO | I331: 1 GAL | J331: Galon | K331: 3.785 | L331: L | M331: 1 | N331: =F331/M331 -> 7308 | O331: =N331/K331 -> 1930.7794
A332: Vistony | B332: Vistony | C332: Quimico/Cuidado vehicular | D332: 1400024 | E332: CAJ06 SILICONA WHITE CON AROMA FRESA DE 1GL | F332: 65619 | G332: 69557 | H332: SILICONA WHITE CON AROMA FRESA | I332: 1 GL | J332: Galon | K332: 3.785 | L332: L | M332: 6 | N332: =F332/M332 -> 10936.5 | O332: =N332/K332 -> 2889.432
A333: Vistony | B333: Vistony | C333: Quimico/Cuidado vehicular | D333: 1400043 | E333: FRA PULVERIZADOR PARA MOTOR DE 650 ML | F333: 2746 | G333: 2911 | H333: PULVERIZADOR PARA MOTOR | I333: 650 ML | J333: Frasco/Botella | K333: 0.65 | L333: L | M333: 1 | N333: =F333/M333 -> 2746 | O333: =N333/K333 -> 4224.6154
A334: Vistony | B334: Vistony | C334: Quimico/Cuidado vehicular | D334: 1400026 | E334: CAJ12 BRILLANTA - PROTEGE Y BRILLA DE 300 ML | F334: 19543 | G334: 20716 | H334: BRILLANTA - PROTEGE Y BRILLA | I334: 300 ML | J334: Sachet/Spray | K334: 0.3 | L334: L | M334: 12 | N334: =F334/M334 -> 1628.5833 | O334: =N334/K334 -> 5428.6111
A335: Vistony | B335: Vistony | C335: Quimico/Cuidado vehicular | D335: 1400045 | E335: FRA LIMPIA TAPIZ VISTONY DE 650 ML | F335: 1448 | G335: 1535 | H335: LIMPIA TAPIZ VISTONY | I335: 650 ML | J335: Frasco/Botella | K335: 0.65 | L335: L | M335: 1 | N335: =F335/M335 -> 1448 | O335: =N335/K335 -> 2227.6923
A336: Vistony | B336: Vistony | C336: Quimico/Cuidado vehicular | D336: 1400035 | E336: CAJ06 SHAMPOO SUPER CONCENTRADO DE GAL | F336: 44776 | G336: 47463 | H336: SHAMPOO SUPER CONCENTRADO | I336: 1 GAL | J336: Galon | K336: 3.785 | L336: L | M336: 6 | N336: =F336/M336 -> 7462.6667 | O336: =N336/K336 -> 1971.6424
... A391: Vistony | B391: Vistony | C391: Lubricante | D391: 1000299 | E391: BAL GEAR OIL GL-5 SAE 75W90 DE 5 GAL | F391: 94688 | G391: 100369 | H391: GEAR OIL GL-5 SAE 75W90 | I391: 5 GAL | J391: Balde | K391: 18.925 | L391: L | M391: 1 | N391: =F391/M391 -> 94688 | O391: =N391/K391 -> 5003.3289
A392: SalfaSur | B392: KUMHO | C392: Neumatico | D392: 240272 | E392: 31X10.5 R15 KL71 109Q K | F392: 115417.19 | H392: 31X10.5 R15 KL71 109Q K | I392: Unidad | J392: Unidad | K392: 1 | L392: Un | M392: 1 | N392: =F392/M392 -> 115417.19 | O392: =N392/K392 -> 115417.19 | P392: 2
A393: SalfaSur | B393: KUMHO | C393: Neumatico | D393: 240276 | E393: 215/75 R15 KL71 106Q 8PR K | F393: 114425.33 | H393: 215/75 R15 KL71 106Q 8PR K | I393: Unidad | J393: Unidad | K393: 1 | L393: Un | M393: 1 | N393: =F393/M393 -> 114425.33 | O393: =N393/K393 -> 114425.33 | P393: 6
A394: SalfaSur | B394: KUMHO | C394: Neumatico | D394: 240079 | E394: 30X9.5 R15 KL71 104Q 6PR K | F394: 96086.653 | H394: 30X9.5 R15 KL71 104Q 6PR K | I394: Unidad | J394: Unidad | K394: 1 | L394: Un | M394: 1 | N394: =F394/M394 -> 96086.653 | O394: =N394/K394 -> 96086.653 | P394: 61
A395: SalfaSur | B395: KUMHO | C395: Neumatico | D395: 240331 | E395: 27X8.5 R14 KL71 6PR K | F395: 80655.667 | H395: 27X8.5 R14 KL71 6PR K | I395: Unidad | J395: Unidad | K395: 1 | L395: Un | M395: 1 | N395: =F395/M395 -> 80655.667 | O395: =N395/K395 -> 80655.667 | P395: 7
A396: SalfaSur | B396: KUMHO | C396: Neumatico | D396: 244243 | E396: 225/60 R16 KR26 98H K | F396: 59516.333 | H396: 225/60 R16 KR26 98H K | I396: Unidad | J396: Unidad | K396: 1 | L396: Un | M396: 1 | N396: =F396/M396 -> 59516.333 | O396: =N396/K396 -> 59516.333 | P396: 8
A397: SalfaSur | B397: KUMHO | C397: Neumatico | D397: 244248 | E397: 215/70 R16 KC53 108T 6PR K | F397: 83348.16 | H397: 215/70 R16 KC53 108T 6PR K | I397: Unidad | J397: Unidad | K397: 1 | L397: Un | M397: 1 | N397: =F397/M397 -> 83348.16 | O397: =N397/K397 -> 83348.16 | P397: 66
A398: SalfaSur | B398: KUMHO | C398: Neumatico | D398: 240497 | E398: 235/60 R17 KL33 102V 4PR K | F398: 93905.333 | H398: 235/60 R17 KL33 102V 4PR K | I398: Unidad | J398: Unidad | K398: 1 | L398: Un | M398: 1 | N398: =F398/M398 -> 93905.333 | O398: =N398/K398 -> 93905.333 | P398: 13
A399: SalfaSur | B399: KUMHO | C399: Neumatico | D399: 240450 | E399: 155/70 R13 KR26 75H 4PR K | F399: 30582.667 | H399: 155/70 R13 KR26 75H 4PR K | I399: Unidad | J399: Unidad | K399: 1 | L399: Un | M399: 1 | N399: =F399/M399 -> 30582.667 | O399: =N399/K399 -> 30582.667 | P399: 2
A400: SalfaSur | B400: KUMHO | C400: Neumatico | D400: 244256 | E400: 235/60 R16 PA31 100V 4PR | F400: 70342.973 | H400: 235/60 R16 PA31 100V 4PR | I400: Unidad | J400: Unidad | K400: 1 | L400: Un | M400: 1 | N400: =F400/M400 -> 70342.973 | O400: =N400/K400 -> 70342.973 | P400: 2
A401: SalfaSur | B401: KUMHO | C401: Neumatico | D401: 241237 | E401: 195/60 R16 KC53 99H K | F401: 61414.547 | H401: 195/60 R16 KC53 99H K | I401: Unidad | J401: Unidad | K401: 1 | L401: Un | M401: 1 | N401: =F401/M401 -> 61414.547 | O401: =N401/K401 -> 61414.547 | P401: 3
A402: SalfaSur | B402: KUMHO | C402: Neumatico | D402: 244306 | E402: 245/75 R16 AT51 109T | F402: 86608.653 | H402: 245/75 R16 AT51 109T | I402: Unidad | J402: Unidad | K402: 1 | L402: Un | M402: 1 | N402: =F402/M402 -> 86608.653 | O402: =N402/K402 -> 86608.653 | P402: 2
A403: SalfaSur | B403: KUMHO | C403: Neumatico | D403: 244395 | E403: 225/60 R16 KH27 98V VT | F403: 59581.387 | H403: 225/60 R16 KH27 98V VT | I403: Unidad | J403: Unidad | K403: 1 | L403: Un | M403: 1 | N403: =F403/M403 -> 59581.387 | O403: =N403/K403 -> 59581.387 | P403: 15
... A614: SalfaSur | B614: AUSTER | C614: Lubricante | D614: 7000069 | E614: AUSTER 75W80 GL-5 1LT | F614: 3198.5714 | H614: AUSTER 75W80 GL-5 | I614: 1 LT | J614: Frasco/Botella | K614: 1 | L614: L | M614: 1 | N614: =F614/M614 -> 3198.5714 | O614: =N614/K614 -> 3198.5714 | P614: 228
A615: Cristian Hughes | B615: Platin | C615: Bateria | D615: PT40B19L | E615: 40B19L (35 Ah - 300 CCA) | F615: 31500 | H615: 40B19L | I615: Unidad | J615: Unidad | K615: 1 | L615: Un | M615: 1 | N615: =F615/M615 -> 31500 | O615: =N615/K615 -> 31500
A616: Cristian Hughes | B616: Platin | C616: Bateria | D616: PT40B19R | E616: 40B19R (35 Ah - 300 CCA) | F616: 31500 | H616: 40B19R | I616: Unidad | J616: Unidad | K616: 1 | L616: Un | M616: 1 | N616: =F616/M616 -> 31500 | O616: =N616/K616 -> 31500
A617: Cristian Hughes | B617: Platin | C617: Bateria | D617: PT40B20L | E617: 40B20L (35 Ah - 300 CCA) | F617: 31500 | H617: 40B20L | I617: Unidad | J617: Unidad | K617: 1 | L617: Un | M617: 1 | N617: =F617/M617 -> 31500 | O617: =N617/K617 -> 31500
A618: Cristian Hughes | B618: Platin | C618: Bateria | D618: PT50B19L | E618: 50B19L (40 Ah - 350 CCA) | F618: 33500 | H618: 50B19L | I618: Unidad | J618: Unidad | K618: 1 | L618: Un | M618: 1 | N618: =F618/M618 -> 33500 | O618: =N618/K618 -> 33500
A619: Cristian Hughes | B619: Platin | C619: Bateria | D619: PT54459 | E619: 54459 (44 Ah 400 CCA) | F619: 33500 | H619: 54459 | I619: Unidad | J619: Unidad | K619: 1 | L619: Un | M619: 1 | N619: =F619/M619 -> 33500 | O619: =N619/K619 -> 33500
A620: Cristian Hughes | B620: Platin | C620: Bateria | D620: PT54316 | E620: 54316 (44 Ah 400 CCA) | F620: 33500 | H620: 54316 | I620: Unidad | J620: Unidad | K620: 1 | L620: Un | M620: 1 | N620: =F620/M620 -> 33500 | O620: =N620/K620 -> 33500
A621: Cristian Hughes | B621: Platin | C621: Bateria | D621: PT60B24L | E621: 60B24L (45 Ah - 400 CCA) | F621: 37990 | H621: 60B24L | I621: Unidad | J621: Unidad | K621: 1 | L621: Un | M621: 1 | N621: =F621/M621 -> 37990 | O621: =N621/K621 -> 37990
A622: Cristian Hughes | B622: Platin | C622: Bateria | D622: PT60B24R | E622: 60B24R (45 Ah 400 CCA) | F622: 37990 | H622: 60B24R | I622: Unidad | J622: Unidad | K622: 1 | L622: Un | M622: 1 | N622: =F622/M622 -> 37990 | O622: =N622/K622 -> 37990
A623: Cristian Hughes | B623: Platin | C623: Bateria | D623: PT55D23L | E623: 55D23L (60 Ah - 500 CCA) | F623: 40500 | H623: 55D23L | I623: Unidad | J623: Unidad | K623: 1 | L623: Un | M623: 1 | N623: =F623/M623 -> 40500 | O623: =N623/K623 -> 40500
A624: Cristian Hughes | B624: Platin | C624: Bateria | D624: PT55D23R | E624: 55D23R (60 Ah - 500 CCA) | F624: 40500 | H624: 55D23R | I624: Unidad | J624: Unidad | K624: 1 | L624: Un | M624: 1 | N624: =F624/M624 -> 40500 | O624: =N624/K624 -> 40500
A625: Cristian Hughes | B625: Platin | C625: Bateria | D625: PTQ85 | E625: Q85 EFB (Start-Stop) (65 Ah - 620 CCA) | F625: 68500 | H625: Q85 EFB (Start-Stop) | I625: Unidad | J625: Unidad | K625: 1 | L625: Un | M625: 1 | N625: =F625/M625 -> 68500 | O625: =N625/K625 -> 68500
A626: Cristian Hughes | B626: Platin | C626: Bateria | D626: PT55566 | E626: 55566 (55 Ah - 390 CCA) | F626: 31500 | H626: 55566 | I626: Unidad | J626: Unidad | K626: 1 | L626: Un | M626: 1 | N626: =F626/M626 -> 31500 | O626: =N626/K626 -> 31500
... A654: Cristian Hughes | B654: Platin | C654: Bateria | D654: PT200 | E654: N200 (200 Ah - 1100 CCA) | F654: 119990 | H654: N200 | I654: Unidad | J654: Unidad | K654: 1 | L654: Un | M654: 1 | N654: =F654/M654 -> 119990 | O654: =N654/K654 -> 119990

Sheet Comparativo_Proveedor
A1: Categoria | B1: Producto (spec) | C1: Segmento | D1: Proveedor | E1: Marca | F1: Codigo SKU | G1: Descripcion SKU | H1: Presentacion | I1: Envase | J1: Costo Unitario (CLP/L, CLP/Kg o CLP/Un) | K1: Mas conveniente
A2: Baterias | B2: Bateria 100 Ah | C2: Construccion (agro) | D2: Cristian Hughes | E2: Platin | F2: PT105D31R | G2: 105D31R (90 Ah - 640 CCA) | H2: Unidad | I2: Unidad | J2: 53900 | K2: SI - mas barato
A3: Baterias | B3: Bateria 100 Ah | C3: Construccion (agro) | D3: SalfaSur | E3: YOKO G&B | F3: 352438 | G3: BATERIA YOKO KR 90AMP NX120-7 | H3: Unidad | I3: Unidad | J3: 69715.2
A4: Baterias | B4: Bateria 120 Ah | C4: Construccion (agro) | D4: Cristian Hughes | E4: Platin | F4: PT120 | G4: N120 (120 Ah - 760 CCA) | H4: Unidad | I4: Unidad | J4: 89990 | K4: SI - mas barato
A5: Baterias | B5: Bateria 120 Ah | C5: Construccion (agro) | D5: SalfaSur | E5: YOKO G&B | F5: 352445 | G5: BATERIA YOKO KR 120AMP N120 | H5: Unidad | I5: Unidad | J5: 100573.4
A6: Baterias | B6: Bateria 150 Ah | C6: Flotas / Construccion | D6: Cristian Hughes | E6: Platin | F6: PT150 | G6: N150 (150 Ah - 1000 CCA) | H6: Unidad | I6: Unidad | J6: 104990 | K6: SI - mas barato
A7: Baterias | B7: Bateria 150 Ah | C7: Flotas / Construccion | D7: SalfaSur | E7: YOKO G&B | F7: 352450 | G7: BATERIA YOKO KR 150AMP N150 | H7: Unidad | I7: Unidad | J7: 129164.3
A8: Baterias | B8: Bateria 150 Ah agro | C8: Construccion (agro) | D8: Cristian Hughes | E8: Platin | F8: PT150 | G8: N150 (150 Ah - 1000 CCA) | H8: Unidad | I8: Unidad | J8: 104990 | K8: SI - mas barato
A9: Baterias | B9: Bateria 150 Ah agro | C9: Construccion (agro) | D9: SalfaSur | E9: YOKO G&B | F9: 352450 | G9: BATERIA YOKO KR 150AMP N150 | H9: Unidad | I9: Unidad | J9: 129164.3
A10: Baterias | B10: Bateria 180 Ah | C10: Flotas / Construccion | D10: Cristian Hughes | E10: Platin | F10: PT180 | G10: N180 (180 Ah - 1100 CCA) | H10: Unidad | I10: Unidad | J10: 119990 | K10: SI - mas barato
A11: Baterias | B11: Bateria 180 Ah agro | C11: Construccion (agro) | D11: Cristian Hughes | E11: Platin | F11: PT180 | G11: N180 (180 Ah - 1100 CCA) | H11: Unidad | I11: Unidad | J11: 119990 | K11: SI - mas barato
A12: Baterias | B12: Bateria 200 Ah | C12: Flotas / Construccion | D12: Cristian Hughes | E12: Platin | F12: PT200 | G12: N200 (200 Ah - 1100 CCA) | H12: Unidad | I12: Unidad | J12: 119990 | K12: SI - mas barato
A13: Baterias | B13: Bateria 200 Ah | C13: Flotas / Construccion | D13: SalfaSur | E13: YOKO G&B | F13: 352465 | G13: BATERIA YOKO KR 200AMP N200 | H13: Unidad | I13: Unidad | J13: 170703.8
A14: Baterias | B14: Bateria 45 Ah | C14: Talleres / Concesionarios | D14: SalfaSur | E14: YOKO G&B | F14: 352410 | G14: BATERIA YOKO KR 35AMP NS40ZL | H14: Unidad | I14: Unidad | J14: 31310.5 | K14: SI - mas barato
A15: Baterias | B15: Bateria 45 Ah | C15: Talleres / Concesionarios | D15: Cristian Hughes | E15: Platin | F15: PT40B19L | G15: 40B19L (35 Ah - 300 CCA) | H15: Unidad | I15: Unidad | J15: 31500
A16: Baterias | B16: Bateria 55 Ah | C16: Talleres / Concesionarios | D16: Cristian Hughes | E16: Platin | F16: PT55566 | G16: 55566 (55 Ah - 390 CCA) | H16: Unidad | I16: Unidad | J16: 31500 | K16: SI - mas barato
A17: Baterias | B17: Bateria 55 Ah | C17: Talleres / Concesionarios | D17: SalfaSur | E17: YOKO G&B | F17: 352447 | G17: BATERIA YOKO KR 45AMP NX100-S6LS | H17: Unidad | I17: Unidad | J17: 41703.4
A18: Baterias | B18: Bateria 60 Ah | C18: Talleres / Concesionarios | D18: Cristian Hughes | E18: Platin | F18: PT55566 | G18: 55566 (55 Ah - 390 CCA) | H18: Unidad | I18: Unidad | J18: 31500 | K18: SI - mas barato
A19: Baterias | B19: Bateria 60 Ah | C19: Talleres / Concesionarios | D19: SalfaSur | E19: YOKO G&B | F19: 352466 | G19: BATERIA YOKO KR 55AMP 55565 | H19: Unidad | I19: Unidad | J19: 44272.3
A20: Baterias | B20: Bateria 65 Ah | C20: Talleres / Concesionarios | D20: Cristian Hughes | E20: Platin | F20: PT55566 | G20: 55566 (55 Ah - 390 CCA) | H20: Unidad | I20: Unidad | J20: 31500 | K20: SI - mas barato
A21: Baterias | B21: Bateria 65 Ah | C21: Talleres / Concesionarios | D21: SalfaSur | E21: YOKO G&B | F21: 352466 | G21: BATERIA YOKO KR 55AMP 55565 | H21: Unidad | I21: Unidad | J21: 44272.3
A22: Baterias | B22: Bateria 70 Ah | C22: Talleres / Concesionarios | D22: Cristian Hughes | E22: Platin | F22: PT55D23L | G22: 55D23L (60 Ah - 500 CCA) | H22: Unidad | I22: Unidad | J22: 40500 | K22: SI - mas barato
A23: Baterias | B23: Bateria 70 Ah | C23: Talleres / Concesionarios | D23: SalfaSur | E23: YOKO G&B | F23: 352460 | G23: SMF 56219 62AMP CCA510 | H23: Unidad | I23: Unidad | J23: 47167.6
A24: Baterias | B24: Bateria 75 Ah | C24: Talleres / Concesionarios / Flotas | D24: Cristian Hughes | E24: Platin | F24: PT85D26L | G24: 85D26L (70 Ah - 550 CCA) | H24: Unidad | I24: Unidad | J24: 43990 | K24: SI - mas barato
A25: Baterias | B25: Bateria 75 Ah | C25: Talleres / Concesionarios / Flotas | D25: SalfaSur | E25: YOKO G&B | F25: 352436 | G25: BATERIA YOKO KR 70AMP NX110-5L | H25: Unidad | I25: Unidad | J25: 59234.7
A26: Baterias | B26: Bateria 80 Ah | C26: Talleres / Concesionarios / Flotas | D26: Cristian Hughes | E26: Platin | F26: PT85D26L | G26: 85D26L (70 Ah - 550 CCA) | H26: Unidad | I26: Unidad | J26: 43990 | K26: SI - mas barato
A27: Baterias | B27: Bateria 80 Ah | C27: Talleres / Concesionarios / Flotas | D27: SalfaSur | E27: YOKO G&B | F27: 352436 | G27: BATERIA YOKO KR 70AMP NX110-5L | H27: Unidad | I27: Unidad | J27: 59234.7
A28: Baterias | B28: Bateria 90 Ah | C28: Talleres / Concesionarios / Flotas | D28: Cristian Hughes | E28: Platin | F28: PT90D26L | G28: 90D26L (80 Ah - 620 CCA) | H28: Unidad | I28: Unidad | J28: 52500 | K28: SI - mas barato
A29: Baterias | B29: Bateria 90 Ah | C29: Talleres / Concesionarios / Flotas | D29: SalfaSur | E29: YOKO G&B | F29: 352438 | G29: BATERIA YOKO KR 90AMP NX120-7 | H29: Unidad | I29: Unidad | J29: 69715.2
A30: Baterias | B30: Bateria 95 Ah | C30: Talleres / Concesionarios / Flotas | D30: Cristian Hughes | E30: Platin | F30: PT105D31R | G30: 105D31R (90 Ah - 640 CCA) | H30: Unidad | I30: Unidad | J30: 53900 | K30: SI - mas barato
A31: Baterias | B31: Bateria 95 Ah | C31: Talleres / Concesionarios / Flotas | D31: SalfaSur | E31: YOKO G&B | F31: 352438 | G31: BATERIA YOKO KR 90AMP NX120-7 | H31: Unidad | I31: Unidad | J31: 69715.2
A32: Grasas | B32: Grasa alta temperatura | C32: Construccion (mineria) | D32: Vistony | E32: Vistony | F32: 1100198 | G32: CIL COMPLEX MOLY NLGI 2 DE 400 LB | H32: 400 LB | I32: Tambor/Cilindro | J32: 7361 | K32: SI - mas barato
A33: Grasas | B33: Grasa complejo de litio | C33: Flotas | D33: Vistony | E33: Vistony | F33: 1100208 | G33: BAL COMPLEJO DE LITIO NLGI 2 DE 16 KG | H33: 16 KG | I33: Balde | J33: 4681.7 | K33: SI - mas barato
A34: Grasas | B34: Grasa de litio EP2 | C34: Construccion (agro) | D34: Vistony | E34: Vistony | F34: 1100003 | G34: BAL EP-2 LITHIUM MULTIPROPOSITO AMARILLO DE 35 LIBRAS | H34: 35 LIBRAS | I34: Balde | J34: 3874.8 | K34: SI - mas barato
A35: Grasas | B35: Grasa multiproposito EP2 | C35: Talleres / Concesionarios | D35: Vistony | E35: Vistony | F35: 1100140 | G35: TAP EP-2 LITHIUM MULTIPROPOSITO AMARILLO DE 210 GRS | H35: 210 GRS | I35: Tarro | J35: 4395.2 | K35: SI - mas barato
A36: Grasas | B36: Grasa para rodamientos | C36: Industria | D36: Vistony | E36: Vistony | F36: 1100040 | G36: TAP H-3 PARA RODAMIENTOS ROJO DE 453 GRS | H36: 453 GRS | I36: Tarro | J36: 4878.6 | K36: SI - mas barato
A37: Lubricantes | B37: 10W30/10W40 CK-4 | C37: Flotas / Construccion | D37: SalfaSur | E37: AUSTER | F37: 7000012 | G37: AUSTER MAXFORCE 10W40 CK-4 20L | H37: 20 L | I37: Balde | J37: 182.7 | K37: SI - mas barato
A38: Lubricantes | B38: 10W30/10W40 CK-4 | C38: Flotas / Construccion | D38: Vistony | E38: Vistony | F38: 1000153 | G38: CIL TRAKOIL 10W30 DE 55 GAL | H38: 55 GAL | I38: Tambor/Cilindro | J38: 2549.7
A39: Lubricantes | B39: 10W40 semisintetico | C39: Talleres / Concesionarios | D39: SalfaSur | E39: AUSTER | F39: 7000011 | G39: AUSTER MAXFORCE 10W40 CK-4 3L | H39: 3 L | I39: Galon | J39: 1361.8 | K39: SI - mas barato
A40: Lubricantes | B40: 10W40 semisintetico | C40: Talleres / Concesionarios | D40: Vistony | E40: Vistony | F40: 1000807 | G40: GL BLINDAX DUO SAE 10W40 DE 4 LT | H40: 4 LT | I40: Galon | J40: 3033
A41: Lubricantes | B41: 15W40 CI-4 | C41: Flotas / Construccion | D41: SalfaSur | E41: AUSTER | F41: 7000007 | G41: AUSTER MAXFORCE 15W40 CK-4 3L | H41: 3 L | I41: Galon | J41: 1191.9 | K41: SI - mas barato
A42: Lubricantes | B42: 15W40 CI-4 | C42: Flotas / Construccion | D42: Vistony | E42: Vistony | F42: 1000469 | G42: CIL FORZA RAYGOLD SAE 15W40 API CK-4 DE 55 GAL | H42: 55 GAL | I42: Tambor/Cilindro | J42: 3333.9
A43: Lubricantes | B43: 15W40 CK-4 | C43: Flotas / Construccion | D43: SalfaSur | E43: AUSTER | F43: 7000007 | G43: AUSTER MAXFORCE 15W40 CK-4 3L | H43: 3 L | I43: Galon | J43: 1191.9 | K43: SI - mas barato
A44: Lubricantes | B44: 15W40 CK-4 | C44: Flotas / Construccion | D44: Vistony | E44: Vistony | F44: 1000469 | G44: CIL FORZA RAYGOLD SAE 15W40 API CK-4 DE 55 GAL | H44: 55 GAL | I44: Tambor/Cilindro | J44: 3333.9
A45: Lubricantes | B45: 5W30 sintetico | C45: Talleres / Concesionarios | D45: SalfaSur | E45: AUSTER | F45: 7000049 | G45: AUSTER MAXTECH PRO RX 5W30 SP/CJ 4LT | H45: 4 LT | I45: Galon | J45: 2863.5 | K45: SI - mas barato
A46: Lubricantes | B46: 5W30 sintetico | C46: Talleres / Concesionarios | D46: Vistony | E46: Vistony | F46: 1000366 | G46: GL ATTOM SAE 5W30 DE 1 GAL | H46: 1 GAL | I46: Galon | J46: 4028.8
A47: Lubricantes | B47: 5W40 sintetico | C47: Talleres / Concesionarios | D47: SalfaSur | E47: AUSTER | F47: 7000007 | G47: AUSTER MAXFORCE 15W40 CK-4 3L | H47: 3 L | I47: Galon | J47: 1191.9 | K47: SI - mas barato
A48: Lubricantes | B48: 5W40 sintetico | C48: Talleres / Concesionarios | D48: Vistony | E48: Vistony | F48: 1000410 | G48: GL FORZA PLUS SAE 15W40 DE 1 GAL | H48: 1 GAL | I48: Galon | J48: 3690.9
A49: Lubricantes | B49: Aceite compresores | C49: Industria | D49: Vistony | E49: Vistony | F49: 1000118 | G49: BAL AIR COMPRESSOR OIL 46 DE 5 GAL | H49: 5 GAL | I49: Balde | J49: 3512.3 | K49: SI - mas barato
A50: Lubricantes | B50: Aceite engranajes | C50: Talleres / Flotas / Industria | D50: Vistony | E50: Vistony | F50: 1000310 | G50: CIL ACEITE TRANSMEC API GL-4 SAE 80W90 DE 55 GAL | H50: 55 GAL | I50: Tambor/Cilindro | J50: 3017.5 | K50: SI - mas barato
A51: Lubricantes | B51: Hidraulico ISO 46 | C51: Construccion / Industria | D51: SalfaSur | E51: AUSTER | F51: 7000056 | G51: AUSTER HYDRO ISO 46 200LT | H51: 200 LT | I51: Tambor/Cilindro | J51: 1833.5 | K51: SI - mas barato
A52: Lubricantes | B52: Hidraulico ISO 46 | C52: Construccion / Industria | D52: Vistony | E52: Vistony | F52: 1000318 | G52: CIL TURBINIUM T ISO 46 DE 55 GAL | H52: 55 GAL | I52: Tambor/Cilindro | J52: 2969.6
A53: Lubricantes | B53: Hidraulico ISO 68 | C53: Construccion / Industria | D53: SalfaSur | E53: AUSTER | F53: 7000058 | G53: AUSTER HYDRO ISO 68 200LT | H53: 200 LT | I53: Tambor/Cilindro | J53: 1845.6 | K53: SI - mas barato
A54: Lubricantes | B54: Hidraulico ISO 68 | C54: Construccion / Industria | D54: Vistony | E54: Vistony | F54: 1000114 | G54: BAL TEXVAC ISO 68 DE 5 GAL | H54: 5 GAL | I54: Balde | J54: 3428.4
A55: Neumaticos | B55: 185/65R15 | C55: Talleres / Concesionarios | D55: SalfaSur | E55: DOUBLE STAR | F55: 210016 | G55: 185/65 R15 DH05 88H | H55: Unidad | I55: Unidad | J55: 26089.1 | K55: SI - mas barato
A56: Neumaticos | B56: 195/65R15 | C56: Talleres / Concesionarios | D56: SalfaSur | E56: KUMHO | F56: 244361 | G56: 195/65 R15 ES31 4PR TL CH | H56: Unidad | I56: Unidad | J56: 48291.7 | K56: SI - mas barato
A57: Neumaticos | B57: 205/55R16 | C57: Talleres / Concesionarios | D57: SalfaSur | E57: DOUBLE STAR | F57: 210069 | G57: 205/55 R16 DH05 91V | H57: Unidad | I57: Unidad | J57: 29248.2 | K57: SI - mas barato
A58: Neumaticos | B58: 245/70R16 | C58: Flotas / Concesionarios | D58: SalfaSur | E58: DOUBLE STAR | F58: 210103 | G58: 245/70 R16 W01 113/110Q | H58: Unidad | I58: Unidad | J58: 65589.3 | K58: SI - mas barato
A59: Neumaticos | B59: 265/60R18 | C59: Flotas / Concesionarios | D59: SalfaSur | E59: DOUBLE STAR | F59: 210063 | G59: 265/60 R18 W01 110T | H59: Unidad | I59: Unidad | J59: 71129.2 | K59: SI - mas barato
A60: Neumaticos | B60: 265/60R18 | C60: Flotas / Concesionarios | D60: SalfaSur | E60: KUMHO | F60: 244788 | G60: 265/60 R18 HP71 110V | H60: Unidad | I60: Unidad | J60: 140362.7
A61: Neumaticos | B61: 265/65R17 | C61: Flotas / Concesionarios | D61: SalfaSur | E61: DOUBLE STAR | F61: 210044 | G61: 265/65 R17 W01 120/117R 10PR | H61: Unidad | I61: Unidad | J61: 76269.3 | K61: SI - mas barato
A62: Neumaticos | B62: 265/70R16 | C62: Flotas / Concesionarios | D62: SalfaSur | E62: DOUBLE STAR | F62: 210104 | G62: 265/70 R16 DS01 112H | H62: Unidad | I62: Unidad | J62: 66053.4 | K62: SI - mas barato
A63: Neumaticos | B63: Camion 295/80R22.5 | C63: Construccion (agro) | D63: SalfaSur | E63: DOUBLE STAR | F63: 210067 | G63: 295/80 R22.5 DSR266 154/152M 18PR | H63: Unidad | I63: Unidad | J63: 147103.3 | K63: SI - mas barato
A64: Neumaticos | B64: Camion 295/80R22.5 | C64: Construccion (agro) | D64: SalfaSur | E64: KUMHO | F64: 244610 | G64: 295/80 R22.5 MD41 16PR 152/148K | H64: Unidad | I64: Unidad | J64: 306044.7
A65: Neumaticos | B65: Tractor 1200 R24 | C65: Construccion (agro) | D65: SalfaSur | E65: DOUBLE STAR | F65: 210118 | G65: 1200 R24 DSR168 160/157L 20PR | H65: Unidad | I65: Unidad | J65: 271616.2 | K65: SI - mas barato
A66: Neumaticos | B66: Tractor/pulveriz. 245/75R16 | C66: Construccion (agro) | D66: SalfaSur | E66: DOUBLE STAR | F66: 210026 | G66: 245/75 R16 W01 114/111R 8PR | H66: Unidad | I66: Unidad | J66: 69607.4 | K66: SI - mas barato
A67: Neumaticos | B67: Tractor/pulveriz. 245/75R16 | C67: Construccion (agro) | D67: SalfaSur | E67: KUMHO | F67: 244306 | G67: 245/75 R16 AT51 109T | H67: Unidad | I67: Unidad | J67: 86608.7
A68: Refrigerantes | B68: Concentrado 50/50 industrial | C68: Industria / Construccion | D68: Vistony | E68: Vistony | F68: 1200086 | G68: GL COOLANT ICE FREEZE SI-ORGANICO (SI-OAT) G12++ 50/50 COLOR ROSA DE 5L | H68: 5 L | I68: Galon | J68: 409 | K68: SI - mas barato
A69: Refrigerantes | B69: Refrig. grupo electrogeno | C69: Construccion | D69: Vistony | E69: Vistony | F69: 1200095 | G69: CIL COOLANT ICE HEAVY-DUTY HYBRID (NOAT) 50/50 EXTENDED LIFE RED DE 55 GL | H69: 55 GL | I69: Tambor/Cilindro | J69: 1895 | K69: SI - mas barato
A70: Refrigerantes | B70: Refrig. maquinaria pesada | C70: Construccion / Flotas | D70: Vistony | E70: Vistony | F70: 1200095 | G70: CIL COOLANT ICE HEAVY-DUTY HYBRID (NOAT) 50/50 EXTENDED LIFE RED DE 55 GL | H70: 55 GL | I70: Tambor/Cilindro | J70: 1895 | K70: SI - mas barato
A71: Refrigerantes | B71: Refrigerante rojo OAT | C71: Talleres / Concesionarios / Flotas | D71: Vistony | E71: Vistony | F71: 1200036 | G71: GL LIQUIDO PARA RADIADOR ROJO - 1 GAL | H71: 1 GAL | I71: Galon | J71: 566.2 | K71: SI - mas barato
A72: Refrigerantes | B72: Refrigerante verde convencional | C72: Talleres / Concesionarios | D72: Vistony | E72: Vistony | F72: 1200010 | G72: GL LIQUIDO PARA RADIADOR VERDE DE 1 GAL | H72: 1 GAL | I72: Galon | J72: 626.2 | K72: SI - mas barato

Sheet Recomendacion_por_Segmento
A1: Categoria | B1: Producto (spec) | C1: Segmento | D1: Prioridad | E1: Proveedor recomendado | F1: Marca | G1: Codigo SKU | H1: Presentacion recomendada | I1: Envase | J1: Costo Unitario (CLP) | K1: Margen B2B | L1: Precio B2B sugerido (CLP) | M1: Mercado Min (CLP) | N1: Mercado Max (CLP) | O1: Brecha vs Mercado Min | P1: N Proveedores comparados | Q1: Nota
A2: Baterias | B2: Bateria 45 Ah | C2: Talleres / Concesionarios | D2: Nivel 1 | E2: SalfaSur | F2: YOKO G&B | G2: 352410 | H2: Unidad | I2: Unidad | J2: 31310.5 | K2: =Portada!$D$10 -> 0.35 | L2: =J2/(1-K2) -> 48170 | M2: 54538 | N2: 67227 | O2: =(M2-L2)/M2 -> 0.11676262 | P2: 2
A3: Baterias | B3: Bateria 55 Ah | C3: Talleres / Concesionarios | D3: Nivel 1 | E3: Cristian Hughes | F3: Platin | G3: PT55566 | H3: Unidad | I3: Unidad | J3: 31500 | K3: =Portada!$D$10 -> 0.35 | L3: =J3/(1-K3) -> 48461.538 | M3: 41176 | N3: 79832 | O3: =(M3-L3)/M3 -> -0.17693653 | P3: 2
A4: Baterias | B4: Bateria 60 Ah | C4: Talleres / Concesionarios | D4: Nivel 1 | E4: Cristian Hughes | F4: Platin | G4: PT55566 | H4: Unidad | I4: Unidad | J4: 31500 | K4: =Portada!$D$10 -> 0.35 | L4: =J4/(1-K4) -> 48461.538 | M4: 62941 | N4: 92437 | O4: =(M4-L4)/M4 -> 0.23004816 | P4: 2
A5: Baterias | B5: Bateria 65 Ah | C5: Talleres / Concesionarios | D5: Nivel 1 | E5: Cristian Hughes | F5: Platin | G5: PT55566 | H5: Unidad | I5: Unidad | J5: 31500 | K5: =Portada!$D$10 -> 0.35 | L5: =J5/(1-K5) -> 48461.538 | P5: 2
A6: Baterias | B6: Bateria 70 Ah | C6: Talleres / Concesionarios | D6: Nivel 1 | E6: Cristian Hughes | F6: Platin | G6: PT55D23L | H6: Unidad | I6: Unidad | J6: 40500 | K6: =Portada!$D$10 -> 0.35 | L6: =J6/(1-K6) -> 62307.692 | M6: 63782 | N6: 92437 | O6: =(M6-L6)/M6 -> 0.023114792 | P6: 2
A7: Baterias | B7: Bateria 75 Ah | C7: Talleres / Concesionarios / Flotas | D7: Nivel 1 | E7: Cristian Hughes | F7: Platin | G7: PT85D26L | H7: Unidad | I7: Unidad | J7: 43990 | K7: =Portada!$D$10 -> 0.35 | L7: =J7/(1-K7) -> 67676.923 | M7: 92437 | N7: 100840 | O7: =(M7-L7)/M7 -> 0.26785894 | P7: 2
A8: Baterias | B8: Bateria 80 Ah | C8: Talleres / Concesionarios / Flotas | D8: Nivel 1 | E8: Cristian Hughes | F8: Platin | G8: PT85D26L | H8: Unidad | I8: Unidad | J8: 43990 | K8: =Portada!$D$10 -> 0.35 | L8: =J8/(1-K8) -> 67676.923 | M8: 79748 | N8: 92353 | O8: =(M8-L8)/M8 -> 0.15136526 | P8: 2
A9: Baterias | B9: Bateria 90 Ah | C9: Talleres / Concesionarios / Flotas | D9: Nivel 1 | E9: Cristian Hughes | F9: Platin | G9: PT90D26L | H9: Unidad | I9: Unidad | J9: 52500 | K9: =Portada!$D$10 -> 0.35 | L9: =J9/(1-K9) -> 80769.231 | M9: 83193 | N9: 117815 | O9: =(M9-L9)/M9 -> 0.029134293 | P9: 2
A10: Baterias | B10: Bateria 95 Ah | C10: Talleres / Concesionarios / Flotas | D10: Nivel 1 | E10: Cristian Hughes | F10: Platin | G10: PT105D31R | H10: Unidad | I10: Unidad | J10: 53900 | K10: =Portada!$D$10 -> 0.35 | L10: =J10/(1-K10) -> 82923.077 | P10: 2
A11: Baterias | B11: Bateria 150 Ah | C11: Flotas / Construccion | D11: Nivel 1 | E11: Cristian Hughes | F11: Platin | G11: PT150 | H11: Unidad | I11: Unidad | J11: 104990 | K11: =Portada!$D$10 -> 0.35 | L11: =J11/(1-K11) -> 161523.08 | M11: 142017 | N11: 168067 | O11: =(M11-L11)/M11 -> -0.1373503 | P11: 2
A12: Baterias | B12: Bateria 180 Ah | C12: Flotas / Construccion | D12: Nivel 1 | E12: Cristian Hughes | F12: Platin | G12: PT180 | H12: Unidad | I12: Unidad | J12: 119990 | K12: =Portada!$D$10 -> 0.35 | L12: =J12/(1-K12) -> 184600 | P12: 1
A13: Baterias | B13: Bateria 200 Ah | C13: Flotas / Construccion | D13: Nivel 1 | E13: Cristian Hughes | F13: Platin | G13: PT200 | H13: Unidad | I13: Unidad | J13: 119990 | K13: =Portada!$D$10 -> 0.35 | L13: =J13/(1-K13) -> 184600 | M13: 190336 | N13: 201681 | O13: =(M13-L13)/M13 -> 0.03013618 | P13: 2
A14: Baterias | B14: Bateria 100 Ah | C14: Construccion (agro) | D14: Nivel 2 | E14: Cristian Hughes | F14: Platin | G14: PT105D31R | H14: Unidad | I14: Unidad | J14: 53900 | K14: =Portada!$D$10 -> 0.35 | L14: =J14/(1-K14) -> 82923.077 | M14: 104958 | N14: 126050 | O14: =(M14-L14)/M14 -> 0.20994039 | P14: 2
A15: Baterias | B15: Bateria 120 Ah | C15: Construccion (agro) | D15: Nivel 2 | E15: Cristian Hughes | F15: Platin | G15: PT120 | H15: Unidad | I15: Unidad | J15: 89990 | K15: =Portada!$D$10 -> 0.35 | L15: =J15/(1-K15) -> 138446.15 | P15: 2
A16: Baterias | B16: Bateria 150 Ah agro | C16: Construccion (agro) | D16: Nivel 2 | E16: Cristian Hughes | F16: Platin | G16: PT150 | H16: Unidad | I16: Unidad | J16: 104990 | K16: =Portada!$D$10 -> 0.35 | L16: =J16/(1-K16) -> 161523.08 | P16: 2
A17: Baterias | B17: Bateria 180 Ah agro | C17: Construccion (agro) | D17: Nivel 2 | E17: Cristian Hughes | F17: Platin | G17: PT180 | H17: Unidad | I17: Unidad | J17: 119990 | K17: =Portada!$D$10 -> 0.35 | L17: =J17/(1-K17) -> 184600 | P17: 1
A18: Neumaticos | B18: 185/65R15 | C18: Talleres / Concesionarios | D18: Nivel 1 | E18: SalfaSur | F18: DOUBLE STAR | G18: 210016 | H18: Unidad | I18: Unidad | J18: 26089.1 | K18: =Portada!$D$10 -> 0.35 | L18: =J18/(1-K18) -> 40137.077 | M18: 29412 | N18: 37815 | O18: =(M18-L18)/M18 -> -0.3646497 | P18: 1
A19: Neumaticos | B19: 195/65R15 | C19: Talleres / Concesionarios | D19: Nivel 1 | E19: SalfaSur | F19: KUMHO | G19: 244361 | H19: Unidad | I19: Unidad | J19: 48291.7 | K19: =Portada!$D$10 -> 0.35 | L19: =J19/(1-K19) -> 74294.923 | M19: 50420 | N19: 67227 | O19: =(M19-L19)/M19 -> -0.47352089 | P19: 1
A20: Neumaticos | B20: 205/55R16 | C20: Talleres / Concesionarios | D20: Nivel 1 | E20: SalfaSur | F20: DOUBLE STAR | G20: 210069 | H20: Unidad | I20: Unidad | J20: 29248.2 | K20: =Portada!$D$10 -> 0.35 | L20: =J20/(1-K20) -> 44997.231 | M20: 33613 | N20: 42017 | O20: =(M20-L20)/M20 -> -0.33868535 | P20: 1
A21: Neumaticos | B21: 215/55R17 | C21: Talleres / Concesionarios | D21: Nivel 1 | E21: SIN MATCH | Q21: Sin producto equivalente en el catalogo actual - revisar manualmente
A22: Neumaticos | B22: 225/65R17 | C22: Talleres / Concesionarios | D22: Nivel 1 | E22: SIN MATCH | Q22: Sin producto equivalente en el catalogo actual - revisar manualmente
A23: Neumaticos | B23: 265/65R17 | C23: Flotas / Concesionarios | D23: Nivel 1 | E23: SalfaSur | F23: DOUBLE STAR | G23: 210044 | H23: Unidad | I23: Unidad | J23: 76269.3 | K23: =Portada!$D$10 -> 0.35 | L23: =J23/(1-K23) -> 117337.38 | M23: 79832 | N23: 100840 | O23: =(M23-L23)/M23 -> -0.4698039 | P23: 1
A24: Neumaticos | B24: 265/70R16 | C24: Flotas / Concesionarios | D24: Nivel 1 | E24: SalfaSur | F24: DOUBLE STAR | G24: 210104 | H24: Unidad | I24: Unidad | J24: 66053.4 | K24: =Portada!$D$10 -> 0.35 | L24: =J24/(1-K24) -> 101620.62 | M24: 75630 | N24: 92437 | O24: =(M24-L24)/M24 -> -0.34365484 | P24: 1
A25: Neumaticos | B25: 245/70R16 | C25: Flotas / Concesionarios | D25: Nivel 1 | E25: SalfaSur | F25: DOUBLE STAR | G25: 210103 | H25: Unidad | I25: Unidad | J25: 65589.3 | K25: =Portada!$D$10 -> 0.35 | L25: =J25/(1-K25) -> 100906.62 | M25: 71429 | N25: 88235 | O25: =(M25-L25)/M25 -> -0.41268414 | P25: 1
A26: Neumaticos | B26: 265/60R18 | C26: Flotas / Concesionarios | D26: Nivel 1 | E26: SalfaSur | F26: DOUBLE STAR | G26: 210063 | H26: Unidad | I26: Unidad | J26: 71129.2 | K26: =Portada!$D$10 -> 0.35 | L26: =J26/(1-K26) -> 109429.54 | M26: 117899 | N26: 134706 | O26: =(M26-L26)/M26 -> 0.071836585 | P26: 1
A27: Neumaticos | B27: Tractor 1200 R24 | C27: Construccion (agro) | D27: Nivel 2 | E27: SalfaSur | F27: DOUBLE STAR | G27: 210118 | H27: Unidad | I27: Unidad | J27: 271616.2 | K27: =Portada!$D$10 -> 0.35 | L27: =J27/(1-K27) -> 417871.08 | P27: 1
A28: Neumaticos | B28: Tractor/pulveriz. 245/75R16 | C28: Construccion (agro) | D28: Nivel 2 | E28: SalfaSur | F28: DOUBLE STAR | G28: 210026 | H28: Unidad | I28: Unidad | J28: 69607.4 | K28: =Portada!$D$10 -> 0.35 | L28: =J28/(1-K28) -> 107088.31 | P28: 1
A29: Neumaticos | B29: Camion 295/80R22.5 | C29: Construccion (agro) | D29: Nivel 2 | E29: SalfaSur | F29: DOUBLE STAR | G29: 210067 | H29: Unidad | I29: Unidad | J29: 147103.3 | K29: =Portada!$D$10 -> 0.35 | L29: =J29/(1-K29) -> 226312.77 | P29: 1
A30: Lubricantes | B30: 5W30 sintetico | C30: Talleres / Concesionarios | D30: Nivel 1 | E30: SalfaSur | F30: AUSTER | G30: 7000049 | H30: 4 LT | I30: Galon | J30: 2863.5 | K30: =Portada!$D$10 -> 0.35 | L30: =J30/(1-K30) -> 4405.3846 | P30: 2
A31: Lubricantes | B31: 5W40 sintetico | C31: Talleres / Concesionarios | D31: Nivel 1 | E31: SalfaSur | F31: AUSTER | G31: 7000007 | H31: 3 L | I31: Galon | J31: 1191.9 | K31: =Portada!$D$10 -> 0.35 | L31: =J31/(1-K31) -> 1833.6923 | P31: 2
A32: Lubricantes | B32: 10W40 semisintetico | C32: Talleres / Concesionarios | D32: Nivel 1 | E32: SalfaSur | F32: AUSTER | G32: 7000011 | H32: 3 L | I32: Galon | J32: 1361.8 | K32: =Portada!$D$10 -> 0.35 | L32: =J32/(1-K32) -> 2095.0769 | P32: 2
A33: Lubricantes | B33: 15W40 CI-4 | C33: Flotas / Construccion | D33: Nivel 1 | E33: SalfaSur | F33: AUSTER | G33: 7000007 | H33: 3 L | I33: Galon | J33: 1191.9 | K33: =Portada!$D$10 -> 0.35 | L33: =J33/(1-K33) -> 1833.6923 | P33: 2
A34: Lubricantes | B34: 15W40 CK-4 | C34: Flotas / Construccion | D34: Nivel 1 | E34: SalfaSur | F34: AUSTER | G34: 7000007 | H34: 3 L | I34: Galon | J34: 1191.9 | K34: =Portada!$D$10 -> 0.35 | L34: =J34/(1-K34) -> 1833.6923 | P34: 2
A35: Lubricantes | B35: 10W30/10W40 CK-4 | C35: Flotas / Construccion | D35: Nivel 1 | E35: SalfaSur | F35: AUSTER | G35: 7000012 | H35: 20 L | I35: Balde | J35: 182.7 | K35: =Portada!$D$10 -> 0.35 | L35: =J35/(1-K35) -> 281.07692 | P35: 2
A36: Lubricantes | B36: UTTO | C36: Construccion (agro) | D36: Nivel 2 | E36: SIN MATCH | Q36: Sin producto equivalente en el catalogo actual - revisar manualmente
A37: Lubricantes | B37: STOU | C37: Construccion (agro) | D37: Nivel 2 | E37: SIN MATCH | Q37: Sin producto equivalente en el catalogo actual - revisar manualmente
A38: Lubricantes | B38: Hidraulico ISO 46 | C38: Construccion / Industria | D38: Nivel 2 | E38: SalfaSur | F38: AUSTER | G38: 7000056 | H38: 200 LT | I38: Tambor/Cilindro | J38: 1833.5 | K38: =Portada!$D$10 -> 0.35 | L38: =J38/(1-K38) -> 2820.7692 | P38: 2
A39: Lubricantes | B39: Hidraulico ISO 68 | C39: Construccion / Industria | D39: Nivel 2 | E39: SalfaSur | F39: AUSTER | G39: 7000058 | H39: 200 LT | I39: Tambor/Cilindro | J39: 1845.6 | K39: =Portada!$D$10 -> 0.35 | L39: =J39/(1-K39) -> 2839.3846 | P39: 2
A40: Lubricantes | B40: Hidraulico ISO 32 | C40: Industria | D40: Nivel 3 | E40: SIN MATCH | Q40: Sin producto equivalente en el catalogo actual - revisar manualmente
A41: Lubricantes | B41: Aceite compresores | C41: Industria | D41: Nivel 3 | E41: Vistony | F41: Vistony | G41: 1000118 | H41: 5 GAL | I41: Balde | J41: 3512.3 | K41: =Portada!$D$10 -> 0.35 | L41: =J41/(1-K41) -> 5403.5385 | P41: 1
A42: Lubricantes | B42: Aceite engranajes | C42: Talleres / Flotas / Industria | D42: Nivel 2 | E42: Vistony | F42: Vistony | G42: 1000310 | H42: 55 GAL | I42: Tambor/Cilindro | J42: 3017.5 | K42: =Portada!$D$10 -> 0.35 | L42: =J42/(1-K42) -> 4642.3077 | P42: 1
A43: Grasas | B43: Grasa multiproposito EP2 | C43: Talleres / Concesionarios | D43: Nivel 2 | E43: Vistony | F43: Vistony | G43: 1100140 | H43: 210 GRS | I43: Tarro | J43: 4395.2 | K43: =Portada!$D$10 -> 0.35 | L43: =J43/(1-K43) -> 6761.8462 | P43: 1
A44: Grasas | B44: Grasa de litio EP2 | C44: Construccion (agro) | D44: Nivel 2 | E44: Vistony | F44: Vistony | G44: 1100003 | H44: 35 LIBRAS | I44: Balde | J44: 3874.8 | K44: =Portada!$D$10 -> 0.35 | L44: =J44/(1-K44) -> 5961.2308 | P44: 1
A45: Grasas | B45: Grasa complejo de litio | C45: Flotas | D45: Nivel 2 | E45: Vistony | F45: Vistony | G45: 1100208 | H45: 16 KG | I45: Balde | J45: 4681.7 | K45: =Portada!$D$10 -> 0.35 | L45: =J45/(1-K45) -> 7202.6154 | P45: 1
A46: Grasas | B46: Grasa para rodamientos | C46: Industria | D46: Nivel 3 | E46: Vistony | F46: Vistony | G46: 1100040 | H46: 453 GRS | I46: Tarro | J46: 4878.6 | K46: =Portada!$D$10 -> 0.35 | L46: =J46/(1-K46) -> 7505.5385 | P46: 1
A47: Grasas | B47: Grasa alta temperatura | C47: Construccion (mineria) | D47: Nivel 3 | E47: Vistony | F47: Vistony | G47: 1100198 | H47: 400 LB | I47: Tambor/Cilindro | J47: 7361 | K47: =Portada!$D$10 -> 0.35 | L47: =J47/(1-K47) -> 11324.615 | P47: 1
A48: Refrigerantes | B48: Refrigerante verde convencional | C48: Talleres / Concesionarios | D48: Nivel 3 | E48: Vistony | F48: Vistony | G48: 1200010 | H48: 1 GAL | I48: Galon | J48: 626.2 | K48: =Portada!$D$10 -> 0.35 | L48: =J48/(1-K48) -> 963.38462 | P48: 1
A49: Refrigerantes | B49: Refrigerante rojo OAT | C49: Talleres / Concesionarios / Flotas | D49: Nivel 3 | E49: Vistony | F49: Vistony | G49: 1200036 | H49: 1 GAL | I49: Galon | J49: 566.2 | K49: =Portada!$D$10 -> 0.35 | L49: =J49/(1-K49) -> 871.07692 | P49: 1
A50: Refrigerantes | B50: Refrigerante azul HOAT | C50: Talleres / Concesionarios | D50: Nivel 3 | E50: SIN MATCH | Q50: Sin producto equivalente en el catalogo actual - revisar manualmente
A51: Refrigerantes | B51: Concentrado 50/50 industrial | C51: Industria / Construccion | D51: Nivel 3 | E51: Vistony | F51: Vistony | G51: 1200086 | H51: 5 L | I51: Galon | J51: 409 | K51: =Portada!$D$10 -> 0.35 | L51: =J51/(1-K51) -> 629.23077 | P51: 1
A52: Refrigerantes | B52: Refrig. grupo electrogeno | C52: Construccion | D52: Nivel 3 | E52: Vistony | F52: Vistony | G52: 1200095 | H52: 55 GL | I52: Tambor/Cilindro | J52: 1895 | K52: =Portada!$D$10 -> 0.35 | L52: =J52/(1-K52) -> 2915.3846 | P52: 1
A53: Refrigerantes | B53: Refrig. maquinaria pesada | C53: Construccion / Flotas | D53: Nivel 3 | E53: Vistony | F53: Vistony | G53: 1200095 | H53: 55 GL | I53: Tambor/Cilindro | J53: 1895 | K53: =Portada!$D$10 -> 0.35 | L53: =J53/(1-K53) -> 2915.3846 | P53: 1

Sheet Resumen_Segmento
A1: RESUMEN POR SEGMENTO — cobertura de catalogo y competitividad vs mercado
A3: Segmento | B3: Productos priorizados | C3: Con match en catalogo | D3: Sin match | E3: Brecha promedio vs Mercado Min | F3: Proveedor mas usado
A4: Concesionarios | B4: 25 | C4: 22 | D4: 3 | E4: -0.1207 | F4: SalfaSur
A5: Construccion | B5: 22 | C5: 20 | D5: 2 | E5: 0.0342 | F5: SalfaSur
A6: Construccion (agro) | B6: 10 | C6: 8 | D6: 2 | E6: 0.2099 | F6: Cristian Hughes
A7: Construccion (mineria) | B7: 1 | C7: 1 | D7: 0 | F7: Vistony
A8: Flotas | B8: 18 | C8: 18 | D8: 0 | E8: -0.0904 | F8: Cristian Hughes
A9: Industria | B9: 7 | C9: 6 | D9: 1 | F9: Vistony
A10: Talleres | B10: 22 | C10: 19 | D10: 3 | E10: -0.0536 | F10: Cristian Hughes

Sheet Notas
A1: COMO SE CONSTRUYO ESTE MODELO
A3: 1. Matriz_Maestra parte de las 653 filas de la Matriz Maestra de Articulos (Cristian Hughes, Vistony, SalfaSur) ya validada, con Tipo, Presentacion, Envase y Precio Unitario calculados por formula.
A5: 2. La hoja Productos_por_Nicho del archivo original del usuario (52 combinaciones producto x segmento, ya priorizadas en Nivel 1/2/3) se uso como la lista maestra de "que se debe vender". Este modelo NO reinventa esa lista — la usa como base y la completa automaticamente con datos reales de la Matriz Maestra.
A7: 3. Para cada uno de esos 52 productos se buscaron TODOS los SKU equivalentes en la Matriz Maestra (por ejemplo "Bateria 45 Ah" se busco en baterias Platin Y en baterias Yoko G&B por amperaje cercano; "5W30 sintetico" se busco por grado SAE en Attom, Sintek y Auster).
A9: 4. De todos los SKU equivalentes encontrados, se filtro por presentacion adecuada al segmento (Talleres/Concesionarios compran formatos chicos: frasco, galon, tarro. Flotas/Construccion/Mineria/Agricola/Industria pueden comprar formatos grandes: bidon, balde, tambor, ademas de los chicos) y se eligio el de menor costo por unidad normalizada (CLP/Litro, CLP/Kg o CLP/Unidad).
A11: 5. Precio B2B sugerido = Costo Unitario / (1 - Margen objetivo, editable en Portada). Se compara contra el precio minimo de mercado ya investigado en la hoja BENCHMARK_Mercado del archivo original (match automatico por categoria y nombre de producto normalizado).
A13: 6. Brecha vs Mercado Min positiva = el precio B2B de RMG queda POR DEBAJO del piso de mercado retail (favorable, hay margen de maniobra). Brecha negativa = el precio B2B calculado ya esta POR ENCIMA del piso retail (revisar margen o proveedor para ese producto).
A15: PRODUCTOS SIN MATCH EN EL CATALOGO ACTUAL (6 de 52) — quedaron marcados en rojo en Recomendacion_por_Segmento:
A16: - Neumaticos 215/55R17 y 225/65R17: medida no disponible en el catalogo Kumho/Double Star/Kenda actual.
A17: - Lubricantes UTTO, STOU e Hidraulico ISO 32: no se identifico un SKU equivalente en Vistony, Cristian Hughes o SalfaSur con esa especificacion exacta.
A18: - Refrigerante azul HOAT: no hay refrigerante azul en el catalogo actual (solo verde, rojo/OAT y formulas heavy-duty).
A19: Accion sugerida: cotizar estos 6 items puntualmente con los proveedores o evaluar si el segmento realmente los necesita en el corto plazo.
... A24: - Brecha vs Mercado solo esta disponible para los productos que ya estaban en la hoja BENCHMARK_Mercado original (28 de 46 productos con match). Los productos nuevos sin benchmark previo no tienen columna de brecha — se recomienda investigar precio de mercado igual que se hizo para los demas.
